kostal/ActualAnalogInputs.py
kostal/ActualBattery.py
kostal/ActualGenerator.py
kostal/ActualGrid.py
kostal/ActualHome.py
kostal/ActualSZeroIn.py
kostal/DxsApi.py
kostal/Home.py
kostal/InfoVersions.py
kostal/SettingsGeneral.py
kostal/StatisticDay.py
kostal/StatisticTotal.py
kostal/__init__.py
pykostal-0.1.0.dist-info/licenses/LICENSE
pykostal-0.1.0.dist-info/METADATA
pykostal-0.1.0.dist-info/WHEEL
pykostal-0.1.0.dist-info/top_level.txt
pykostal-0.1.0.dist-info/RECORD
