Metadata-Version: 2.4
Name: pykostal
Version: 0.1.0
Summary: package to communicate with Kostal Piko inverters
Author-email: Andreas Rehn <rehn.andreas86@gmail.com>, David Scheidt <scheidt.dav@gmail.com>
License-Expression: MIT
Project-URL: Homepage, https://github.com/DAMEK86/pykostal
Project-URL: Repository, https://github.com/DAMEK86/pykostal
Classifier: Development Status :: 5 - Production/Stable
Classifier: Intended Audience :: Developers
Classifier: Intended Audience :: End Users/Desktop
Classifier: Topic :: Home Automation
Classifier: Topic :: Software Development :: Libraries
Classifier: Natural Language :: English
Classifier: Operating System :: OS Independent
Classifier: Programming Language :: Python :: 3
Classifier: Programming Language :: Python :: 3.9
Classifier: Programming Language :: Python :: 3.10
Classifier: Programming Language :: Python :: 3.11
Classifier: Programming Language :: Python :: 3.12
Classifier: Programming Language :: Python :: 3.13
Classifier: Framework :: AsyncIO
Requires-Python: >=3.9
License-File: LICENSE
Requires-Dist: async_timeout>=4.0.0
Requires-Dist: aiohttp>=3.6.2
Provides-Extra: dev
Requires-Dist: pytest>=3.7; extra == "dev"
Requires-Dist: twine; extra == "dev"
Requires-Dist: tox; extra == "dev"
Dynamic: license-file
